{
	"configurations" : 
	[
		{
			"directories" : 
			[
				{
					"build" : ".",
					"hasInstallRule" : true,
					"jsonFile" : "directory-.-020f1e50304d5d2e4801.json",
					"minimumCMakeVersion" : 
					{
						"string" : "3.15"
					},
					"projectIndex" : 0,
					"source" : ".",
					"targetIndexes" : 
					[
						0,
						1,
						2,
						3
					]
				}
			],
			"name" : "",
			"projects" : 
			[
				{
					"directoryIndexes" : 
					[
						0
					],
					"name" : "cpp02_service",
					"targetIndexes" : 
					[
						0,
						1,
						2,
						3
					]
				}
			],
			"targets" : 
			[
				{
					"directoryIndex" : 0,
					"id" : "cpp02_service_uninstall::@6890427a1f51a3e7e1df",
					"jsonFile" : "target-cpp02_service_uninstall-81241e1edf9f4a8e65b8.json",
					"name" : "cpp02_service_uninstall",
					"projectIndex" : 0
				},
				{
					"directoryIndex" : 0,
					"id" : "demo01_server::@6890427a1f51a3e7e1df",
					"jsonFile" : "target-demo01_server-7c738038b6a8a376d803.json",
					"name" : "demo01_server",
					"projectIndex" : 0
				},
				{
					"directoryIndex" : 0,
					"id" : "demo02_client::@6890427a1f51a3e7e1df",
					"jsonFile" : "target-demo02_client-425588da3e263add89ae.json",
					"name" : "demo02_client",
					"projectIndex" : 0
				},
				{
					"directoryIndex" : 0,
					"id" : "uninstall::@6890427a1f51a3e7e1df",
					"jsonFile" : "target-uninstall-db1a259c4cc1633fba5a.json",
					"name" : "uninstall",
					"projectIndex" : 0
				}
			]
		}
	],
	"kind" : "codemodel",
	"paths" : 
	{
		"build" : "/home/haixin/ws01_plumbing/build/cpp02_service",
		"source" : "/home/haixin/ws01_plumbing/src/cpp02_service"
	},
	"version" : 
	{
		"major" : 2,
		"minor" : 6
	}
}
